ML/__init__.py
ML/_modidx.py
ML/core.py
ML/decisiontree.py
ML/knn.py
ML/linearregression.py
ML/logisticregression.py
MLexamples-0.0.5.dist-info/LICENSE
MLexamples-0.0.5.dist-info/METADATA
MLexamples-0.0.5.dist-info/WHEEL
MLexamples-0.0.5.dist-info/entry_points.txt
MLexamples-0.0.5.dist-info/top_level.txt
MLexamples-0.0.5.dist-info/RECORD
