Metadata-Version: 2.1
Name: MLexamples
Version: 0.0.5
Summary: Machine Learning
Home-page: https://github.com/bthek1/ML
Author: Benedict Thekkel
Author-email: bthekkel1@gmail.com
License: Apache Software License 2.0
Keywords: nbdev jupyter notebook python
Classifier: Development Status :: 4 - Beta
Classifier: Intended Audience :: Developers
Classifier: Natural Language :: English
Classifier: Programming Language :: Python :: 3.7
Classifier: Programming Language :: Python :: 3.8
Classifier: Programming Language :: Python :: 3.9
Classifier: Programming Language :: Python :: 3.10
Classifier: License :: OSI Approved :: Apache Software License
Requires-Python: >=3.7
License-File: LICENSE
Requires-Dist: jupyter
Requires-Dist: jupyterlab
Requires-Dist: nbdev
Requires-Dist: jupyterlab-quarto
Requires-Dist: seaborn
Requires-Dist: scikit-learn
Requires-Dist: pandas
Requires-Dist: matplotlib
Requires-Dist: plotly
Requires-Dist: opencv-python
Requires-Dist: fastai
Provides-Extra: dev
